cangling/__init__.py
cangling/logger/__init__.py
cangling/logger/message_sender.py
cangling/workflow/__init__.py
cangling/workflow/workflow.py
cangling_ai-0.1.12.dist-info/METADATA
cangling_ai-0.1.12.dist-info/WHEEL
cangling_ai-0.1.12.dist-info/top_level.txt
cangling_ai-0.1.12.dist-info/RECORD
