Metadata-Version: 2.4
Name: cangling-ai
Version: 0.1.12
Summary: cangling ai library
Author-email: zhangjianshe <zhangjianshe@gmail.com>
Requires-Python: >=3.10
Requires-Dist: kafka-python==2.0.2
Requires-Dist: loguru>=0.7.3
